matomo_cli/__init__.py
matomo_cli/api.py
matomo_cli/cli.py
matomo_cli/environment.py
matomo_cli/metrics.py
matomo_cli/prometheus.py
matomo_cli-0.1.11.dist-info/LICENSE.md
matomo_cli-0.1.11.dist-info/METADATA
matomo_cli-0.1.11.dist-info/WHEEL
matomo_cli-0.1.11.dist-info/entry_points.txt
matomo_cli-0.1.11.dist-info/RECORD
