Metadata-Version: 2.1
Name: matomo-cli
Version: 0.1.11
Summary: CLI and Prometheus exporter for Matomo
License: GPL-3.0-or-later
Author: Mikke Schirén
Author-email: mikke.schiren@digitalist.com
Requires-Python: >=3.12,<4.0
Classifier: License :: OSI Approved :: GNU General Public License v3 or later (GPLv3+)
Classifier: Programming Language :: Python :: 3
Classifier: Programming Language :: Python :: 3.12
Requires-Dist: click (>=8.1.7,<9.0.0)
Requires-Dist: prometheus-client (>=0.21.0,<0.22.0)
Requires-Dist: requests (>=2.32.3,<3.0.0)
Requires-Dist: rich-click (>=1.8.3,<2.0.0)
